jims_petstore_sdk/__init__.py
jims_petstore_sdk/sdk.py
jims_petstore_sdk/hooks/__init__.py
jims_petstore_sdk/hooks/hook.py
jims_petstore_sdk/models/__init__.py
jims_petstore_sdk/models/base.py
jims_petstore_sdk/models/pet.py
jims_petstore_sdk/models/utils/cast_models.py
jims_petstore_sdk/models/utils/json_map.py
jims_petstore_sdk/net/__init__.py
jims_petstore_sdk/net/environment/__init__.py
jims_petstore_sdk/net/environment/environment.py
jims_petstore_sdk/net/headers/__init__.py
jims_petstore_sdk/net/headers/base_header.py
jims_petstore_sdk/net/request_chain/__init__.py
jims_petstore_sdk/net/request_chain/request_chain.py
jims_petstore_sdk/net/request_chain/handlers/__init__.py
jims_petstore_sdk/net/request_chain/handlers/base_handler.py
jims_petstore_sdk/net/request_chain/handlers/hook_handler.py
jims_petstore_sdk/net/request_chain/handlers/http_handler.py
jims_petstore_sdk/net/request_chain/handlers/retry_handler.py
jims_petstore_sdk/net/transport/__init__.py
jims_petstore_sdk/net/transport/request.py
jims_petstore_sdk/net/transport/request_error.py
jims_petstore_sdk/net/transport/response.py
jims_petstore_sdk/net/transport/serializer.py
jims_petstore_sdk/net/transport/utils.py
jims_petstore_sdk/services/__init__.py
jims_petstore_sdk/services/pets.py
jims_petstore_sdk/services/utils/base_service.py
jims_petstore_sdk/services/utils/default_headers.py
jims_petstore_sdk/services/utils/validator.py
jims_petstore_sdk-1.0.0.dist-info/METADATA
jims_petstore_sdk-1.0.0.dist-info/WHEEL
jims_petstore_sdk-1.0.0.dist-info/top_level.txt
jims_petstore_sdk-1.0.0.dist-info/RECORD
